mcp_server_sentry_xhs/__init__.py
mcp_server_sentry_xhs/__main__.py
mcp_server_sentry_xhs/server.py
mcp_server_sentry_xhs/test.py
mcp_server_sentry_xhs-0.6.4.dist-info/METADATA
mcp_server_sentry_xhs-0.6.4.dist-info/WHEEL
mcp_server_sentry_xhs-0.6.4.dist-info/entry_points.txt
mcp_server_sentry_xhs-0.6.4.dist-info/RECORD
