Metadata-Version: 2.4
Name: mcp-server-sentry-xhs
Version: 0.6.4
Summary: MCP server for retrieving issues from sentry.io
Requires-Python: >=3.10
Requires-Dist: anthropic>=0.49.0
Requires-Dist: httpx>=0.28.0
Requires-Dist: mcp[cli]>=1.0.0
Requires-Dist: openai>=1.68.2
Requires-Dist: python-dotenv>=1.0.1
